{
  "main": {
    "id": "3f0aed537bc9bc42",
    "type": "split",
    "children": [
      {
        "id": "fd96338a17609865",
        "type": "tabs",
        "children": [
          {
            "id": "4887c39ba5b7b9f5",
            "type": "leaf",
            "state": {
              "type": "empty",
              "state": {}
            }
          }
        ]
      }
    ],
    "direction": "vertical"
  },
  "left": {
    "id": "a803d7d809bfafcb",
    "type": "split",
    "children": [
      {
        "id": "53a8b4504231fe77",
        "type": "tabs",
        "children": [
          {
            "id": "a9c033008c99906c",
            "type": "leaf",
            "state": {
              "type": "file-explorer",
              "state": {
                "sortOrder": "alphabetical"
              }
            }
          },
          {
            "id": "b9755e4b99bc58e9",
            "type": "leaf",
            "state": {
              "type": "search",
              "state": {
                "query": "",
                "matchingCase": false,
                "explainSearch": false,
                "collapseAll": false,
                "extraContext": false,
                "sortOrder": "alphabetical"
              }
            }
          },
          {
            "id": "eef074144b3fd639",
            "type": "leaf",
            "state": {
              "type": "bookmarks",
              "state": {}
            }
          }
        ]
      }
    ],
    "direction": "horizontal",
    "width": 229.5
  },
  "right": {
    "id": "df3371eaebed66e9",
    "type": "split",
    "children": [
      {
        "id": "62db329fab9073d5",
        "type": "tabs",
        "children": [
          {
            "id": "36ab70aff675fc6d",
            "type": "leaf",
            "state": {
              "type": "backlink",
              "state": {
                "collapseAll": false,
                "extraContext": false,
                "sortOrder": "alphabetical",
                "showSearch": false,
                "searchQuery": "",
                "backlinkCollapsed": false,
                "unlinkedCollapsed": true
              }
            }
          },
          {
            "id": "b57fb88e51befda1",
            "type": "leaf",
            "state": {
              "type": "outgoing-link",
              "state": {
                "linksCollapsed": false,
                "unlinkedCollapsed": true
              }
            }
          },
          {
            "id": "739bbe47af14f08f",
            "type": "leaf",
            "state": {
              "type": "tag",
              "state": {
                "sortOrder": "frequency",
                "useHierarchy": true
              }
            }
          },
          {
            "id": "18f3c6fd4c047dc7",
            "type": "leaf",
            "state": {
              "type": "outline",
              "state": {}
            }
          },
          {
            "id": "f92634b381d09202",
            "type": "leaf",
            "state": {
              "type": "all-properties",
              "state": {
                "sortOrder": "frequency"
              }
            }
          },
          {
            "id": "b6274e313101a862",
            "type": "leaf",
            "state": {
              "type": "advanced-tables-toolbar",
              "state": {}
            }
          }
        ],
        "currentTab": 5
      }
    ],
    "direction": "horizontal",
    "width": 300,
    "collapsed": true
  },
  "left-ribbon": {
    "hiddenItems": {
      "switcher:Ouvrir le sélecteur rapide": false,
      "graph:Ouvrir la vue graphique": false,
      "canvas:Créer une nouvelle toile": false,
      "daily-notes:Ouvrir la note quotidienne": false,
      "templates:Insérer le modèle": false,
      "command-palette:Ouvrir la palette de commandes": false,
      "table-editor-obsidian:Advanced Tables Toolbar": false
    }
  },
  "active": "4887c39ba5b7b9f5",
  "lastOpenFiles": [
    "Quebec/Administration/Administration.md",
    "Quebec/Administration/QUEBEC formulaire_SE_401-Q-102.pdf",
    "Quebec/Administration/Formulaire SE401-Q-104 stages.pdf",
    "Quebec/Infos Formulaire SE401 Q 102.pdf",
    "Quebec/Formalités dimmigration.pdf",
    "Quebec/Etudier au Québec.pdf",
    "Quebec/Accord de reconnaissance titre dingenieur.pdf",
    "Quebec/Administration/SE401-Q-106.pdf",
    "Quebec/Administration",
    "Quebec/Journée internationale des assistants de langue.pdf",
    "Quebec/Quebec.md",
    "SAE/SAE.md",
    "SAE/Base de Données/Base de Données.md",
    "SAE/Base de Données/Cas transport (Co-voiturage).md",
    "SAE/Base de Données/Modélisation Mocodo.md",
    "Pasted image 20231123091538.png",
    "Quebec/UQAC/UQAC.md",
    "Quebec/UQAC/Cours UQAC INFO.pdf",
    "Quebec/ETS/ETS.md",
    "Quebec/ETS.md",
    "Quebec/UQAC.md",
    "Quebec/ETUDIER AU CANADA - QUEBEC.md",
    "conflict-files-obsidian-git.md",
    "Economie/Cour 1/Schéma économie politique.canvas",
    "Economie/Cour 1/Prise de note cour 1.md",
    "Economie/Economie.md",
    "Base de Données/Opérations/Opérations.md",
    "Base de Données/Opérations/Opération ensemblistes.md",
    "Base de Données/Base de Données.md",
    "SAE/Environement Economie/Environnement économique et écologique.md",
    "SAE/Environement Economie/Environement Economie.md",
    "SAE/Environement Economie/Consigne rédaction dossier.md",
    "PPP/Séance 1-2, métiers de l'informatique.md",
    "Base de Données/TP/tp4/Exo 2.2.md",
    "Base de Données/TP/tp4/Exo 2.1.md",
    "Base de Données/TP/TP3.md",
    "PPP/Séance 1, métiers de l'informatique.md",
    "Anglais Technique/Help Desk/Typical Helpdesk.canvas",
    "Base de Données/TP/tp2/MCD/MCD.svg",
    "Initiation-dev/Algo/quicksort.png",
    "Architecture-système/Introduction/IEEE754/IEEE-754.canvas",
    "Gestion-de-Projet/Entreprise/fonctionement-économique.canvas",
    "Gestion-de-Projet/Entreprise/Stratégie/Business_Model_Canvas.png",
    "Anglais Technique/Vocabulary/Compound Word.canvas",
    "Gestion-de-Projet/Entreprise/TP/tp_création_entreprise/Asteria_logo_1.png",
    "Gestion-de-Projet/Entreprise/tp_création_entreprise/saturn_psychedelique.png"
  ]
}