{
  "main": {
    "id": "3f0aed537bc9bc42",
    "type": "split",
    "children": [
      {
        "id": "a8d89dd295b0e177",
        "type": "tabs",
        "children": [
          {
            "id": "d66e8167241ca4da",
            "type": "leaf",
            "state": {
              "type": "empty",
              "state": {}
            }
          }
        ]
      }
    ],
    "direction": "vertical"
  },
  "left": {
    "id": "a803d7d809bfafcb",
    "type": "split",
    "children": [
      {
        "id": "53a8b4504231fe77",
        "type": "tabs",
        "children": [
          {
            "id": "a9c033008c99906c",
            "type": "leaf",
            "state": {
              "type": "file-explorer",
              "state": {
                "sortOrder": "alphabetical"
              }
            }
          },
          {
            "id": "b9755e4b99bc58e9",
            "type": "leaf",
            "state": {
              "type": "search",
              "state": {
                "query": "",
                "matchingCase": false,
                "explainSearch": false,
                "collapseAll": false,
                "extraContext": false,
                "sortOrder": "alphabetical"
              }
            }
          },
          {
            "id": "eef074144b3fd639",
            "type": "leaf",
            "state": {
              "type": "bookmarks",
              "state": {}
            }
          }
        ]
      }
    ],
    "direction": "horizontal",
    "width": 200
  },
  "right": {
    "id": "df3371eaebed66e9",
    "type": "split",
    "children": [
      {
        "id": "62db329fab9073d5",
        "type": "tabs",
        "children": [
          {
            "id": "36ab70aff675fc6d",
            "type": "leaf",
            "state": {
              "type": "backlink",
              "state": {
                "file": "Economie/Shémas/Schéma répartition richesse & Valeur ajouté.canvas",
                "collapseAll": false,
                "extraContext": false,
                "sortOrder": "alphabetical",
                "showSearch": false,
                "searchQuery": "",
                "backlinkCollapsed": false,
                "unlinkedCollapsed": true
              }
            }
          },
          {
            "id": "b57fb88e51befda1",
            "type": "leaf",
            "state": {
              "type": "outgoing-link",
              "state": {
                "file": "Economie/Shémas/Schéma répartition richesse & Valeur ajouté.canvas",
                "linksCollapsed": false,
                "unlinkedCollapsed": true
              }
            }
          },
          {
            "id": "739bbe47af14f08f",
            "type": "leaf",
            "state": {
              "type": "tag",
              "state": {
                "sortOrder": "frequency",
                "useHierarchy": true
              }
            }
          },
          {
            "id": "18f3c6fd4c047dc7",
            "type": "leaf",
            "state": {
              "type": "outline",
              "state": {
                "file": "Economie/Shémas/Schéma répartition richesse & Valeur ajouté.canvas"
              }
            }
          },
          {
            "id": "f92634b381d09202",
            "type": "leaf",
            "state": {
              "type": "all-properties",
              "state": {
                "sortOrder": "frequency",
                "showSearch": false,
                "searchQuery": ""
              }
            }
          },
          {
            "id": "b6274e313101a862",
            "type": "leaf",
            "state": {
              "type": "advanced-tables-toolbar",
              "state": {}
            }
          }
        ],
        "currentTab": 5
      }
    ],
    "direction": "horizontal",
    "width": 300,
    "collapsed": true
  },
  "left-ribbon": {
    "hiddenItems": {
      "switcher:Ouvrir le sélecteur rapide": false,
      "graph:Ouvrir la vue graphique": false,
      "canvas:Créer une nouvelle toile": false,
      "daily-notes:Ouvrir la note quotidienne": false,
      "templates:Insérer le modèle": false,
      "command-palette:Ouvrir la palette de commandes": false,
      "table-editor-obsidian:Advanced Tables Toolbar": false
    }
  },
  "active": "a9c033008c99906c",
  "lastOpenFiles": [
    "Economie/Shémas/schéma prestataire et client.canvas",
    "Economie/Shémas/Schéma Pouvoir d'Achat.canvas",
    "Economie/Shémas/schéma PIB Pays.canvas",
    "Economie/Shémas/Schéma économie politique.canvas",
    "Economie/Shémas/BUT1-DiffPoliEco.pdf",
    "Economie/Shémas/BUT1-CircuitEco.pdf",
    "Economie/Chap 3/BUT1Ch3Eco.pdf",
    "Economie/Chap 2/BUT1Ch2Eco.pdf",
    "Economie/Chap 1/Chap 1.md",
    "Economie/Chap 1/BUT1Ch1Eco.pdf",
    "Economie/Economie.md",
    "Economie/TD/Chauvel Sacha TD économie.pdf",
    "Economie/TD/lu129761ucoyx.tmp",
    "Economie/TD/lu129761ucoyt.tmp",
    "SAE/SAE.md",
    "SAE/Base de Données/Base de Données.md",
    "SAE/PubCDI/SAE-RecueilBesoins-Lea-Clement-Rafael-Sacha/post insta 1.png",
    "SAE/PubCDI/SAE-RecueilBesoins-Lea-Clement-Rafael-Sacha/story.png",
    "SAE/PubCDI/SAE-RecueilBesoins-Lea-Clement-Rafael-Sacha/programme.png",
    "SAE/PubCDI/SAE-RecueilBesoins-Lea-Clement-Rafael-Sacha/post insta 2.png",
    "SAE/PubCDI/SAE-RecueilBesoins-Lea-Clement-Rafael-Sacha/post insta 3.png",
    "SAE/PubCDI/SAE-RecueilBesoins-Lea-Clement-Rafael-Sacha/marque-pages.png",
    "SAE/PubCDI/SAE-RecueilBesoins-Lea-Clement-Rafael-Sacha/concours.png",
    "SAE/PubCDI/SAE-RecueilBesoins-Lea-Clement-Rafael-Sacha/affiche.png",
    "SAE/PubCDI/SAE-RecueilBesoins-Lea-Clement-Rafael-Sacha",
    "Economie/odtSrc/BUT1Ch3Eco.odt",
    "Economie/TD/Réponses TD.md",
    "Economie/TD/Tableau evolution PIB Français Wikipedia.png",
    "Economie/TD/Graphque evolution PIB Français INSEE.png",
    "Economie/Shémas/Schéma répartition richesse & Valeur ajouté.canvas",
    "Economie/Chap 2/Chap 2 Prise de notes.md",
    "Economie/Chap 1/Chap 1 Prise de note.md",
    "SAE/Base de Données/SQL.md",
    "SAE/Base de Données/Modélisation Mocodo.md",
    "Base de Données/Base de Données.md",
    "conflict-files-obsidian-git.md",
    "SAE/PubCDI/PubCDI.md",
    "SAE/PubCDI/Idée de design.md",
    "SAE/Base de Données/Cas transport (Co-voiturage).md",
    "Economie/Cour 1/Réponses TD.md",
    "Economie/Cour 1/schéma prestataire et client.canvas",
    "Economie/Cour 1/Chap 2 Prise de notes.md",
    "Economie/Cour 1/Prise de note cour 1.md",
    "Bash/Bash.md",
    "Bash/Droits et Administration.md",
    "Bash/tldr - Too Long, Didn't Read.md",
    "Bash/Recherche de fichiers et dossiers.md",
    "Bash/Mise à jour.md",
    "Bash/Gestion des processus.md",
    "Bash/Exécution de cmd chainé.md",
    "Bash/Déplacement dans les dossiers.md",
    "Economie/Cour 1/Schéma Pouvoir d'Achat.canvas",
    "Economie/Cour 1/Schéma économie politique.canvas",
    "Economie/Cour 1/Schéma répartition richesse & Valeur ajouté.canvas",
    "Economie/Cour 1/schéma PIB d'un pays.canvas"
  ]
}