{
  "main": {
    "id": "3f0aed537bc9bc42",
    "type": "split",
    "children": [
      {
        "id": "cf4b9bd087cef54a",
        "type": "tabs",
        "children": [
          {
            "id": "746281088a85e3a8",
            "type": "leaf",
            "pinned": true,
            "state": {
              "type": "graph",
              "state": {},
              "pinned": true
            }
          },
          {
            "id": "19774bc53bd2d5b3",
            "type": "leaf",
            "pinned": true,
            "state": {
              "type": "pdf",
              "state": {
                "file": "Dev-Web/Introduction/r1.02_cm_2023.pdf"
              },
              "pinned": true
            }
          }
        ],
        "currentTab": 1
      }
    ],
    "direction": "vertical"
  },
  "left": {
    "id": "a803d7d809bfafcb",
    "type": "split",
    "children": [
      {
        "id": "53a8b4504231fe77",
        "type": "tabs",
        "children": [
          {
            "id": "a9c033008c99906c",
            "type": "leaf",
            "state": {
              "type": "file-explorer",
              "state": {
                "sortOrder": "alphabetical"
              }
            }
          },
          {
            "id": "b9755e4b99bc58e9",
            "type": "leaf",
            "state": {
              "type": "search",
              "state": {
                "query": "mad",
                "matchingCase": false,
                "explainSearch": false,
                "collapseAll": false,
                "extraContext": false,
                "sortOrder": "alphabetical"
              }
            }
          },
          {
            "id": "eef074144b3fd639",
            "type": "leaf",
            "state": {
              "type": "bookmarks",
              "state": {}
            }
          }
        ]
      }
    ],
    "direction": "horizontal",
    "width": 200
  },
  "right": {
    "id": "df3371eaebed66e9",
    "type": "split",
    "children": [
      {
        "id": "62db329fab9073d5",
        "type": "tabs",
        "children": [
          {
            "id": "36ab70aff675fc6d",
            "type": "leaf",
            "state": {
              "type": "backlink",
              "state": {
                "file": "Dev-Web/Introduction/r1.02_cm_2023.pdf",
                "collapseAll": false,
                "extraContext": false,
                "sortOrder": "alphabetical",
                "showSearch": false,
                "searchQuery": "",
                "backlinkCollapsed": false,
                "unlinkedCollapsed": true
              }
            }
          },
          {
            "id": "b57fb88e51befda1",
            "type": "leaf",
            "state": {
              "type": "outgoing-link",
              "state": {
                "file": "Dev-Web/Introduction/r1.02_cm_2023.pdf",
                "linksCollapsed": false,
                "unlinkedCollapsed": true
              }
            }
          },
          {
            "id": "739bbe47af14f08f",
            "type": "leaf",
            "state": {
              "type": "tag",
              "state": {
                "sortOrder": "frequency",
                "useHierarchy": true
              }
            }
          },
          {
            "id": "18f3c6fd4c047dc7",
            "type": "leaf",
            "state": {
              "type": "outline",
              "state": {
                "file": "Dev-Web/Introduction/r1.02_cm_2023.pdf"
              }
            }
          },
          {
            "id": "f92634b381d09202",
            "type": "leaf",
            "state": {
              "type": "all-properties",
              "state": {
                "sortOrder": "frequency"
              }
            }
          }
        ]
      }
    ],
    "direction": "horizontal",
    "width": 300,
    "collapsed": true
  },
  "left-ribbon": {
    "hiddenItems": {
      "switcher:Ouvrir le sélecteur rapide": false,
      "graph:Ouvrir la vue graphique": false,
      "canvas:Créer une nouvelle toile": false,
      "daily-notes:Ouvrir la note quotidienne": false,
      "templates:Insérer le modèle": false,
      "command-palette:Ouvrir la palette de commandes": false,
      "table-editor-obsidian:Advanced Tables Toolbar": false
    }
  },
  "active": "19774bc53bd2d5b3",
  "lastOpenFiles": [
    "README.md",
    "Dev-Web/Introduction/r1.02_cm_2023.pdf",
    "Dev-Web/Introduction/Introduction.md",
    "Dev-Web/Introduction/Introduction CSS.md",
    "Dev-Web/tp1/tp1.md",
    "Dev-Web/Dev-Web.md",
    "Gestion-de-Projet/Entreprise/Management des Hommes/L'école des Relations Humaines.md",
    "Gestion-de-Projet/Entreprise/Entreprise.md",
    "Gestion-de-Projet/Gestion-de-Projet.md",
    "Communication/Résumé exercices/Résumé exercices.md",
    "Communication/Résumé exercices/Albert Camus - Réflexion sur la Guillotine.md",
    "Communication/Résumé exercices/Voici le temps du monde fini - Albert Jacquard.md",
    "communication/Résumé exercice/lu1231672vllu.tmp",
    "communication/Résumé exercice/lu1231672vllr.tmp",
    "communication/Résumé exercice/lu1231672vllo.tmp",
    "communication/Résumé exercice/lu1231672vlll.tmp",
    "communication/Résumé exercice/lu1231672vlli.tmp",
    "Communication/communication.md",
    "communication/Résumé exercice/lu1231672vlld.tmp",
    "Initiation-dev/Algo/ALG3 Récursivité.md",
    "Initiation-dev/Algo/recursivite.pdf",
    "Initiation-dev/Algo/src_recursivite/sous-chaine.go",
    "Initiation-dev/Algo/src_recursivite/recursif-iteratif.go",
    "Initiation-dev/go/go.md",
    "Initiation-dev/Initiation-dev.md",
    "Gestion-de-Projet/Entreprise/Management des Hommes/L'école Classique.md",
    "Communication/Exposé/Exposé.md",
    "Communication/Résumé exercice/Voici le temps du monde fini - Albert Jacquard.md",
    "Communication/Résumé exercice/Résumé exercice.md",
    "Communication/Communication.md",
    "SAE/Sudoku/Sudoku.md",
    "Maths/Logique/Propriété-et-Definitions/Toolbox.md",
    "Maths/Logique/Prédicats/Quantificateurs (∀ & ∃).md",
    "Maths/Logique/Prédicats/Prédicats.md",
    "Maths/Logique/Prédicats/Prédicat.md",
    "Maths/Logique/Prédicats/Propositions.md",
    "Gestion-de-Projet/Entreprise/tp_création_entreprise/Asteria_logo_1.png",
    "Gestion-de-Projet/Entreprise/tp_création_entreprise/saturn_psychedelique.png"
  ]
}